adf_lib/__init__.py
adf_lib/constants/__init__.py
adf_lib/constants/enums.py
adf_lib/exceptions/__init__.py
adf_lib/exceptions/validation.py
adf_lib/models/__init__.py
adf_lib/models/document.py
adf_lib/models/link.py
adf_lib/models/table.py
adf_lib/models/text.py
adf_lib-0.2.0.dist-info/LICENSE
adf_lib-0.2.0.dist-info/METADATA
adf_lib-0.2.0.dist-info/WHEEL
adf_lib-0.2.0.dist-info/top_level.txt
adf_lib-0.2.0.dist-info/RECORD
