Metadata-Version: 2.2
Name: adf_lib
Version: 0.2.0
Summary: A Python library for creating and manipulating ADF (Atlassian Document Format) documents
Author-email: Dimuthu Lakmal <info@lakmal.dev>
License: MIT License
Project-URL: Homepage, https://github.com/lakmal98/adf-lib
Project-URL: Bug Tracker, https://github.com/lakmal98/adf-lib/issues
Project-URL: Documentation, https://github.com/lakmal98/adf-lib
Keywords: adf,atlassian,document,format,markup
Classifier: Development Status :: 3 - Alpha
Classifier: Intended Audience :: Developers
Classifier: License :: OSI Approved :: MIT License
Classifier: Programming Language :: Python :: 3
Classifier: Programming Language :: Python :: 3.8
Classifier: Programming Language :: Python :: 3.9
Classifier: Programming Language :: Python :: 3.10
Classifier: Programming Language :: Python :: 3.11
Classifier: Topic :: Software Development :: Libraries :: Python Modules
Classifier: Topic :: Text Processing :: Markup
Requires-Python: >=3.8
License-File: LICENSE
